bmfstock.py
setup.py
bmfstock.egg-info/PKG-INFO
bmfstock.egg-info/SOURCES.txt
bmfstock.egg-info/dependency_links.txt
bmfstock.egg-info/top_level.txt
test/testItemPaper.py