Metadata-Version: 1.1
Name: bmfstock
Version: 0.4
Summary: Library to retrieve info about equity from BMF Bovespa
Home-page: UNKNOWN
Author: Christofer Bertonha
Author-email: christoferbertonha@gmail.com
License: LGPL3
Platform: UNKNOWN
Classifier: Development Status :: 4 - Beta
Classifier: Intended Audience :: Developers
Classifier: Intended Audience :: End Users/Desktop
Classifier: License :: OSI Approved :: GNU Library or Lesser General Public License (LGPL)
Classifier: Natural Language :: English
Classifier: Operating System :: OS Independent
Classifier: Programming Language :: Python
Classifier: Topic :: Software Development :: Libraries
